solana_nfts/__init__.py
solana_nfts/src/__init__.py
solana_nfts/src/connection.py
solana_nfts/src/constants.py
solana_nfts-0.0.5.dist-info/LICENSE
solana_nfts-0.0.5.dist-info/METADATA
solana_nfts-0.0.5.dist-info/WHEEL
solana_nfts-0.0.5.dist-info/top_level.txt
solana_nfts-0.0.5.dist-info/RECORD
